MANIFEST.in
README.rst
setup.py
tutor_minio_tmp.egg-info/PKG-INFO
tutor_minio_tmp.egg-info/SOURCES.txt
tutor_minio_tmp.egg-info/dependency_links.txt
tutor_minio_tmp.egg-info/entry_points.txt
tutor_minio_tmp.egg-info/top_level.txt
tutorminiotmp/__init__.py
tutorminiotmp/plugin.py
tutorminiotmp/patches/cms-env
tutorminiotmp/patches/https-create
tutorminiotmp/patches/k8s-deployments
tutorminiotmp/patches/k8s-ingress-certificates
tutorminiotmp/patches/k8s-ingress-rules
tutorminiotmp/patches/k8s-ingress-tls-hosts
tutorminiotmp/patches/k8s-services
tutorminiotmp/patches/k8s-volumes
tutorminiotmp/patches/lms-env
tutorminiotmp/patches/local-docker-compose-nginx-aliases
tutorminiotmp/patches/local-docker-compose-services
tutorminiotmp/patches/nginx-extra
tutorminiotmp/patches/openedx-auth
tutorminiotmp/patches/openedx-common-settings
tutorminiotmp/patches/openedx-lms-common-settings
tutorminiotmp/templates/minio/hooks/minio-client/pre-init