Metadata-Version: 1.2
Name: tutor-minio-tmp
Version: 0.0.5
Summary: A Tutor plugin for object storage in MinIO
Home-page: https://docs.tutor.overhang.io/
Author: weijie
Author-email: wejie00@foxmail.com
License: AGPLv3
Platform: UNKNOWN
Classifier: Development Status :: 3 - Alpha
Classifier: Intended Audience :: Developers
Classifier: License :: OSI Approved :: GNU Affero General Public License v3
Classifier: Operating System :: OS Independent
Classifier: Programming Language :: Python
Classifier: Programming Language :: Python :: 3.5
Classifier: Programming Language :: Python :: 3.6
Classifier: Programming Language :: Python :: 3.7
Requires-Python: >=3.5
